LICENSE
README.md
setup.cfg
setup.py
Centre.PyCS.egg-info/PKG-INFO
Centre.PyCS.egg-info/SOURCES.txt
Centre.PyCS.egg-info/dependency_links.txt
Centre.PyCS.egg-info/entry_points.txt
Centre.PyCS.egg-info/requires.txt
Centre.PyCS.egg-info/top_level.txt
pycs/Connector.py
pycs/__init__.py
pycs/clientex.py
pycs/keys.py
pycs/api/API.py
pycs/api/__init__.py
pycs/api/constants.py
pycs/api/ttypes.py
pycs/apidiag/API_DIAG.py
pycs/apidiag/__init__.py
pycs/apidiag/constants.py
pycs/apidiag/ttypes.py
pycs/general/__init__.py
pycs/general/constants.py
pycs/general/ttypes.py