Metadata-Version: 2.1
Name: Centre.PyCS
Version: 0.1
Summary: Credits Blockchain Implementation in Python
Home-page: https://github.com/akaitrade/Centre.PyCS
Author: BK
Author-email: basknappers@gmail.com
License: UNKNOWN
Download-URL: https://github.com/akaitrade/Centre.PyCS/archive/refs/tags/0.1.0-Beta.tar.gz
Platform: UNKNOWN
Classifier: Programming Language :: Python :: 3
Classifier: License :: OSI Approved :: MIT License
Classifier: Operating System :: OS Independent
License-File: LICENSE
